MANIFEST.in
README.txt
run_tests.py
setup.cfg
setup.py
doc/CC-BY-SA.txt
doc/agpl-3.0.txt
doc/api/ELVIS_logo-framework.png
doc/api/Makefile
doc/api/about.rst
doc/api/conf.py
doc/api/favicon.ico
doc/api/geom_ribbon-6.png
doc/api/index.rst
doc/api/install_and_test.rst
doc/api/modules.rst
doc/api/tutorial-melodic_ngrams.rst
doc/api/tutorial-workflowmanager.rst
doc/api/vis-1-128.png
doc/api/vis.analyzers.experimenters.rst
doc/api/vis.analyzers.indexers.rst
doc/api/vis.analyzers.rst
doc/api/vis.models.rst
vis/__init__.py
vis/optional_requirements.txt
vis/requirements.txt
vis/travis_requirements.txt
vis/workflow.py
vis/analyzers/__init__.py
vis/analyzers/experimenter.py
vis/analyzers/indexer.py
vis/analyzers/experimenters/__init__.py
vis/analyzers/experimenters/aggregator.py
vis/analyzers/experimenters/barchart.py
vis/analyzers/experimenters/dendrogram.py
vis/analyzers/experimenters/frequency.py
vis/analyzers/experimenters/template.py
vis/analyzers/indexers/__init__.py
vis/analyzers/indexers/active_voices.py
vis/analyzers/indexers/approach.py
vis/analyzers/indexers/contour.py
vis/analyzers/indexers/dissonance.py
vis/analyzers/indexers/fermata.py
vis/analyzers/indexers/interval.py
vis/analyzers/indexers/meter.py
vis/analyzers/indexers/ngram.py
vis/analyzers/indexers/noterest.py
vis/analyzers/indexers/offset.py
vis/analyzers/indexers/over_bass.py
vis/analyzers/indexers/repeat.py
vis/analyzers/indexers/template.py
vis/analyzers/indexers/windexer.py
vis/corpora/.DS_Store
vis/corpora/__init__.py
vis/corpora/Bach/Anna-Magdalena-Notebook_O-Ewigkeit-Du-Donnerwort.xml
vis/corpora/Bach/Cantata-16_No-5_Geliebter-Jesu-Du-Allein.xml
vis/corpora/Bach/Choral-62_Wer-nur-den-lieben-Gott-laesst-walten.xml
vis/corpora/Bach/Chorale-26_O-Ewigkeit-Du-Donnerwort.xml
vis/corpora/Bach/Chorale-274_O-Ewigkeit-Du-Donnerwort.xml
vis/corpora/Bach/Invention-No-3.xml
vis/corpora/Bach/Invention-No-4.xml
vis/corpora/Haydn/Haydn_Op-76_No-3_2-0-Theme.xml
vis/corpora/Haydn/Haydn_Op-76_No-3_2-1-Var.xml
vis_framework.egg-info/PKG-INFO
vis_framework.egg-info/SOURCES.txt
vis_framework.egg-info/dependency_links.txt
vis_framework.egg-info/requires.txt
vis_framework.egg-info/top_level.txt